CHANGELOG.txt
LICENCE.txt
MANIFEST.in
README.txt
setup.py
test.py
python_redex.egg-info/PKG-INFO
python_redex.egg-info/SOURCES.txt
python_redex.egg-info/dependency_links.txt
python_redex.egg-info/top_level.txt
redex/__init__.py
redex/action.py
redex/lexical_analysis.py
redex/split.py
redex/wildcards.py
redex.egg-info/SOURCES.txt
redex.egg-info/dependency_links.txt
redex.egg-info/top_level.txt